aissemble_machine_learning_inference/generated/__init__.py
aissemble_machine_learning_inference/generated/bootstrap_base.py
aissemble_machine_learning_inference/generated/dictionary/__init__.py
aissemble_machine_learning_inference/generated/dictionary/date_as_seconds_since_epoch_base.py
aissemble_machine_learning_inference/generated/dictionary/event_category_base.py
aissemble_machine_learning_inference/generated/dictionary/event_kind_base.py
aissemble_machine_learning_inference/generated/dictionary/event_outcome_base.py
aissemble_machine_learning_inference/generated/dictionary/ip_address_base.py
aissemble_machine_learning_inference/generated/dictionary/port_base.py
aissemble_machine_learning_inference/generated/inference/__init__.py
aissemble_machine_learning_inference/generated/inference/grpc/__init__.py
aissemble_machine_learning_inference/generated/inference/grpc/generated/__init__.py
aissemble_machine_learning_inference/generated/inference/grpc/generated/inference_payload_definition_pb2.py
aissemble_machine_learning_inference/generated/inference/grpc/generated/inference_payload_definition_pb2_grpc.py
aissemble_machine_learning_inference/generated/inference/grpc/inference_api_grpc_base.py
aissemble_machine_learning_inference/generated/inference/grpc/inference_api_pb2.py
aissemble_machine_learning_inference/generated/inference/grpc/inference_api_pb2_grpc.py
aissemble_machine_learning_inference/generated/inference/rest/__init__.py
aissemble_machine_learning_inference/generated/inference/rest/inference_payload_definition.py
aissemble_machine_learning_inference/generated/record/__init__.py
aissemble_machine_learning_inference/generated/record/adversarial_threat_prediction_base.py
aissemble_machine_learning_inference/generated/record/adversarial_threat_prediction_field.py
aissemble_machine_learning_inference/generated/record/event_log_entry_base.py
aissemble_machine_learning_inference/generated/record/event_log_entry_field.py
aissemble_machine_learning_inference-2.0.0.dist-info/LICENSE
aissemble_machine_learning_inference-2.0.0.dist-info/METADATA
aissemble_machine_learning_inference-2.0.0.dist-info/WHEEL
aissemble_machine_learning_inference-2.0.0.dist-info/RECORD
